trellis/__init__.py
trellis/_base_client.py
trellis/_client.py
trellis/_compat.py
trellis/_constants.py
trellis/_exceptions.py
trellis/_files.py
trellis/_models.py
trellis/_qs.py
trellis/_resource.py
trellis/_response.py
trellis/_streaming.py
trellis/_types.py
trellis/_version.py
trellis/py.typed
trellis/_utils/__init__.py
trellis/_utils/_logs.py
trellis/_utils/_proxy.py
trellis/_utils/_reflection.py
trellis/_utils/_resources_proxy.py
trellis/_utils/_streams.py
trellis/_utils/_sync.py
trellis/_utils/_transform.py
trellis/_utils/_typing.py
trellis/_utils/_utils.py
trellis/lib/.keep
trellis/resources/__init__.py
trellis/resources/assets.py
trellis/resources/projects.py
trellis/resources/transforms/__init__.py
trellis/resources/transforms/transforms.py
trellis/types/__init__.py
trellis/types/asset_delete_response.py
trellis/types/asset_list_params.py
trellis/types/asset_upload_params.py
trellis/types/assets.py
trellis/types/project_create_params.py
trellis/types/project_create_response.py
trellis/types/project_delete_response.py
trellis/types/project_list_params.py
trellis/types/project_list_response.py
trellis/types/transform_autoschema_response.py
trellis/types/transform_create_params.py
trellis/types/transform_create_response.py
trellis/types/transform_list_params.py
trellis/types/transform_list_response.py
trellis/types/transform_update_params.py
trellis/types/transform_update_response.py
trellis/types/data_sources/__init__.py
trellis/types/events/__init__.py
trellis/types/events/jobs.py
trellis/types/events/subscriptions/__init__.py
trellis/types/templates/__init__.py
trellis/types/transforms/__init__.py
trellis/types/transforms/validations/__init__.py
trellis_python-2.42.2.dist-info/METADATA
trellis_python-2.42.2.dist-info/WHEEL
trellis_python-2.42.2.dist-info/licenses/LICENSE
trellis_python-2.42.2.dist-info/RECORD
